{
  "generated_at": "2026-06-10T02:28:42.495Z",
  "count": 3,
  "issues": [
    {
      "id": 4627135688,
      "number": 3,
      "title": "[遗缺点子] 反菜谱省钱做饭",
      "body": "### 点子名称\n\n反菜谱省钱做饭\n\n### 一句话描述\n\n做一个网页工具，让用户输入家里已有食材、预算、人数和饮食限制，反向生成一周菜单和购物清单，优先复用食材、减少浪费和每天想吃什么的决策压力。\n\n\n### 访问地址\n\n_No response_\n\n### 是否上线\n\n- [ ] 已上线\n\n### 开源地址\n\n_No response_\n\n### 卡住或遗弃原因\n\n时间不够，优先级下降\n\n### 其他原因说明\n\n_No response_\n\n### 技术栈\n\n_No response_\n\n### 已做工作\n\n前端可以使用 React / Vue / Next.js 实现食材输入、菜单生成、购物清单、替换菜品和结果保存。\n\n### 接盘建议\n\n_No response_",
      "html_url": "https://github.com/ipwangxin/AbandonedIdeas/issues/3",
      "created_at": "2026-06-10T01:44:43Z",
      "updated_at": "2026-06-10T01:44:43Z",
      "user": {
        "login": "ipwangxin",
        "html_url": "https://github.com/ipwangxin"
      },
      "labels": [
        "abandoned"
      ]
    },
    {
      "id": 4622512453,
      "number": 2,
      "title": "需求变更审计与成本控制工具",
      "body": "### 点子名称\n\n需求变更审计与成本控制工具\n\n### 一句话描述\n\n\n一个面向软件外包、定制开发、甲乙方协作场景的需求变更记录工具，用来记录需求基线、变更申请、影响评估、审批确认和成本变化，减少甲方频繁改需求但没有留痕的问题。\n\n### 访问地址\n\n_No response_\n\n### 是否上线\n\n_No response_\n\n### 开源地址\n\n_No response_\n\n### 卡住或遗弃原因\n\n推广困难，找不到用户\n\n### 技术栈\n\n未定\n\n### 已做工作\n\n已经梳理出核心场景：\n\n- 开发前确认需求基线\n- 甲方提出需求变更\n- 乙方评估变更影响，包括工期、成本、风险\n- 甲方确认或驳回\n- 系统保留完整操作记录\n- 最终可导出变更记录，用于验收、结算、争议处理\n\n\n### 接盘建议\n\n建议先不要做成完整项目管理系统，而是做一个非常轻量的“需求变更留痕 + 成本影响确认”工具。\n\n\n### 接盘建议\n\n_No response_",
      "html_url": "https://github.com/ipwangxin/AbandonedIdeas/issues/2",
      "created_at": "2026-06-09T13:43:08Z",
      "updated_at": "2026-06-09T14:05:43Z",
      "user": {
        "login": "huangmaozhao",
        "html_url": "https://github.com/huangmaozhao"
      },
      "labels": [
        "abandoned"
      ]
    },
    {
      "id": 4601769031,
      "number": 1,
      "title": "弹幕游戏sass 平台",
      "body": "### [遗缺点子] 点子名称\n\n弹幕大空袭\n\n### 一句话描述\n\n做弹幕游戏sass化的功能，针对游戏主播，或者不会弹幕的\n\n### 当前状态\n\n其他\n\n### 上线地址\n\nhttps://game.swep.top/\n\n### 开源地址\n\n_No response_\n\n### 卡住或遗弃原因\n\n商业模式不清晰\n\n### 技术栈\n\nvue做sass 管理端，golang做后端，web游戏端使用的是Phaser来实现\n\n### 已做工作\n\n 已经完成了前端开发，还未接入官方弹幕，后端完成了一半\n\n### 接盘建议\n\n暂无\n\n### 联系方式或补充链接\n\n_No response_",
      "html_url": "https://github.com/ipwangxin/AbandonedIdeas/issues/1",
      "created_at": "2026-06-06T03:50:35Z",
      "updated_at": "2026-06-06T04:17:07Z",
      "user": {
        "login": "ipwangxin",
        "html_url": "https://github.com/ipwangxin"
      },
      "labels": [
        "abandoned"
      ]
    }
  ]
}